[
  {
    "id": "proj001",
    "title": "Исследование влияния температуры на ферментацию",
    "researcher": "доктор Петренко А.В.",
    "budget": 250000,
    "isActive": true,
    "startDate": "2024-01-15",
    "tags": ["биохимия", "ферментация", "температура"],
    "endDate": "2025-12-31"
  },
  {
    "id": "proj002",
    "title": "Разработка нового антибиотика",
    "researcher": "профессор Сидоренко М.І.",
    "budget": 500000,
    "isActive": true,
    "startDate": "2023-09-01",
    "tags": ["фармакология", "антибиотики", "микробиология"],
    "endDate": "2026-08-31"
  },
  {
    "id": "proj003",
    "title": "Анализ загрязнения водоемов",
    "researcher": "ассистент Коваленко О.П.",
    "budget": 120000,
    "isActive": false,
    "startDate": "2022-03-10",
    "tags": ["экология", "вода", "химический анализ"],
    "endDate": "2023-12-31"
  }
]
